README.txt
pycrastinate.py
setup.py
pycrastinate.egg-info/PKG-INFO
pycrastinate.egg-info/SOURCES.txt
pycrastinate.egg-info/dependency_links.txt
pycrastinate.egg-info/top_level.txt