Metadata-Version: 1.1
Name: pycrastinate
Version: 0.1.0
Summary: Keep your TODO, FIXME, etc. under control by triggering actions, generating reports, date/author/custom filtering, automated e-mails and more
Home-page: https://github.com/isaacbernat/pycrastinate
Author: Isaac Bernat
Author-email: isaac.bernat@gmail.com
License: None
Keywords: todo,fixme,xxx,comments,extract,clean,report,creep,git
Platform: UNKNOWN
Classifier: Programming Language :: Python
Classifier: Programming Language :: Python :: 2
Classifier: Programming Language :: Python :: 2.7
Classifier: Programming Language :: Python :: 3
Classifier: Development Status :: 4 - Beta
Classifier: Environment :: Console
Classifier: Intended Audience :: Developers
Classifier: Intended Audience :: Information Technology
Classifier: Natural Language :: English
Classifier: Operating System :: OS Independent
Classifier: Topic :: Documentation
Classifier: Topic :: Software Development
Classifier: Topic :: Software Development :: Bug Tracking
Classifier: Topic :: Software Development :: Documentation
Classifier: Topic :: Software Development :: Quality Assurance
Classifier: Topic :: Software Development :: Version Control
Classifier: Topic :: Utilities
